ChangeLog
VERSION
makerelease.py
setup.py
doc/index.html
ez_setup/README.txt
ez_setup/__init__.py
nsis/pydirstat.nsi
nsis/version.nsi
res/msvcr71.dll
res/pydirstat.ico
src/pds-config.py
src/pdshtml.py
src/pdssvg.py
src/pdsswf.py
src/pydirstat.py
src/dirstat/CommandLine.py
src/dirstat/Configuration.py
src/dirstat/DirInfo.py
src/dirstat/Dumper.py
src/dirstat/FileInfo.py
src/dirstat/FileInfoList.py
src/dirstat/FileProvider.py
src/dirstat/FileProviderBase.py
src/dirstat/FileProviderLocal.py
src/dirstat/FileTree.py
src/dirstat/SimuQT.py
src/dirstat/SizeColorProvider.py
src/dirstat/TreemapTile.py
src/dirstat/TreemapView.py
src/dirstat/__init__.py
src/dirstat/__version__.py
src/dirstat/walker.py
src/dirstat/Dumpers/HTML.py
src/dirstat/Dumpers/Ming.py
src/dirstat/Dumpers/SVG.py
src/dirstat/Dumpers/__init__.py
src/dirstat/Dumpers/HTML.py
src/dirstat/Dumpers/Ming.py
src/dirstat/Dumpers/SVG.py
src/dirstat/Dumpers/__init__.py
src/pydirstat.egg-info/PKG-INFO
src/pydirstat.egg-info/SOURCES.txt
src/pydirstat.egg-info/dependency_links.txt
src/pydirstat.egg-info/not-zip-safe
src/pydirstat.egg-info/top_level.txt
