Metadata-Version: 1.0
Name: pydirstat
Version: 0.9.15
Summary: Show statistics informations for a directory in HTML, SVG, or Flash.
Home-page: http://pydirstat.berlios.de/
Author: Arthibus Gissehel
Author-email: public-pds-setup@giss.ath.cx
License: UNKNOWN
Platform: UNKNOWN
Classifier: Development Status :: 4 - Beta
Classifier: Environment :: Console
Classifier: Environment :: Web Environment
Classifier: Environment :: Win32 (MS Windows)
Classifier: Intended Audience :: End Users/Desktop
Classifier: Intended Audience :: System Administrators
Classifier: License :: OSI Approved :: GNU General Public License (GPL)
Classifier: Operating System :: Microsoft :: Windows
Classifier: Operating System :: OS Independent
Classifier: Programming Language :: Python
Classifier: Topic :: System :: Filesystems
Classifier: Topic :: System :: Systems Administration
